orion_data_analyst-1.1.4.dist-info/licenses/LICENSE
src/__init__.py
src/cli.py
src/config.py
src/agent/__init__.py
src/agent/graph.py
src/agent/nodes.py
src/agent/state.py
src/utils/__init__.py
src/utils/cache.py
src/utils/formatter.py
src/utils/rate_limiter.py
src/utils/schema_fetcher.py
src/utils/token_tracker.py
src/utils/visualizer.py
orion_data_analyst-1.1.4.dist-info/METADATA
orion_data_analyst-1.1.4.dist-info/WHEEL
orion_data_analyst-1.1.4.dist-info/entry_points.txt
orion_data_analyst-1.1.4.dist-info/top_level.txt
orion_data_analyst-1.1.4.dist-info/RECORD
