Metadata-Version: 2.4
Name: orion-data-analyst
Version: 1.1.4
Summary: AI-powered BigQuery data analysis agent with natural language interface
Home-page: https://github.com/gavrielhan/orion-data-analyst
Author: Gavriel Hannuna
Author-email: Gavriel Hannuna <gavriel.hannuna@gmail.com>
License: MIT
Project-URL: Homepage, https://github.com/gavrielhan/orion-data-analyst
Project-URL: Bug Reports, https://github.com/gavrielhan/orion-data-analyst/issues
Project-URL: Source, https://github.com/gavrielhan/orion-data-analyst
Project-URL: Documentation, https://github.com/gavrielhan/orion-data-analyst#readme
Keywords: data-analysis,bigquery,ai,nlp,sql,gemini,analytics
Classifier: Development Status :: 4 - Beta
Classifier: Intended Audience :: Developers
Classifier: Intended Audience :: Science/Research
Classifier: Topic :: Scientific/Engineering :: Artificial Intelligence
Classifier: Topic :: Database
Classifier: License :: OSI Approved :: MIT License
Classifier: Programming Language :: Python :: 3
Classifier: Programming Language :: Python :: 3.8
Classifier: Programming Language :: Python :: 3.9
Classifier: Programming Language :: Python :: 3.10
Classifier: Programming Language :: Python :: 3.11
Requires-Python: >=3.8
License-File: LICENSE
Requires-Dist: langgraph>=0.2.0
Requires-Dist: langchain>=0.3.0
Requires-Dist: google-cloud-bigquery>=3.25.0
Requires-Dist: google-generativeai>=0.3.0
Requires-Dist: db-dtypes
Requires-Dist: pandas>=2.0.0
Requires-Dist: python-dotenv>=1.0.0
Requires-Dist: pydantic>=2.0.0
Requires-Dist: typing-extensions>=4.12.0
Requires-Dist: matplotlib>=3.7.0
Requires-Dist: seaborn>=0.12.0
Dynamic: author
Dynamic: home-page
Dynamic: license-file
Dynamic: requires-python
